{"MlsNumber":"11689547","Area":"2369.3 pi²","BuildingAssessment":"$345,000","YearBuilt":"1963","Garage":"Fitted, Single width","HeatingEnergy":"Electricity","HeatingSystem":"Space heating baseboards, Electric baseboard units","LotAssessment":"$110,100","LotDepth":"81.7 ft","LotFrontage":"29 ft","MunicipalTax":"$4,099.00","Parking":"Outdoor (1), Garage (1)","Proximity":"Hospital, Park - green area, Elementary school, High school, Public transport, Bicycle path","SchoolTax":"$842.00","WaterSupply":"Municipality","SewageSystem":"Municipal sewer","Zoning":"Residential"}