{"MlsNumber":"14033283","Area":"3500 pi²","BuildingAssessment":"$140,900","YearBuilt":"1970","Garage":"Heated, Single width","HeatingEnergy":"Electricity","HeatingSystem":"Hot water","LotAssessment":"$112,200","LotDepth":"73.5 ft","LotFrontage":"47.5 ft","MunicipalTax":"$2,436.00","Parking":"Outdoor (1), Garage (1)","Proximity":"Park - green area, Elementary school, High school, Public transport, Bicycle path","SchoolTax":"$462.00","WaterSupply":"Municipality","SewageSystem":"Municipal sewer","Zoning":"Residential"}