{"MlsNumber":"20857011","BuildingAssessment":"$303,200.00","YearBuilt":"1974","LivingArea":"1921.0 Square Feet","Garage":"Attached, Double width or more","HeatingEnergy":"Heating oil","HeatingSystem":"Forced air","LotAssessment":"$182,700.00","LotDepth":"117.0 Feet","LotFrontage":"82.0 Feet","Area":"9594.00 Square Feet","MunicipalTax":"$4,365.00","Parking":"Driveway, Garage","Proximity":"Highway, Elementary school, High school, Commuter train, Public transportation","SchoolTax":"$849.00","WaterSupply":"Municipality","SewageSystem":"Municipality","Zoning":"RESI"}