{"MlsNumber":"15887916","YearBuilt":"1986","Garage":"Heated, Double width or more","Area":"5,506 SF","Zoning":"Residential","Parking":"Garage : 2, Driveway : 2","Proximity":"Commuter train, Elementary school, CEGEP, Park, Bicycle path, Hospital, Highway, High school, Public transportation","MunicipalTax":"$7,384.00","SchoolTax":"$1,200.00","MunicipalAssessment":"$910,900.00","HeatingEnergy":"Electricity","WaterSupply":"Municipality","SewageSystem":"Municipality","Pool":"Inground, Heated, Salt water"}