{"MlsNumber":"19256519","YearBuilt":"1950","Garage":"Built-in, Double width or more","FloorCovering":"Flexible floor coverings, Wood","Area":"3,772 SF","Zoning":"Residential","Parking":"Garage : 2, Driveway : 2","Proximity":"Park, Hospital, Commuter train, CEGEP, Public transportation, High school, Metro, University, Elementary school, Bicycle path, Highway","MunicipalTax":"$4,188.00","SchoolTax":"$1,001.00","MunicipalAssessment":"$587,700.00","HeatingEnergy":"Electricity","WaterSupply":"Municipality","SewageSystem":"Municipality","LivingArea":"2,400 SF"}